flask_jsonschema.py
Flask_JsonSchemaValidator-0.3.0.dist-info/LICENSE
Flask_JsonSchemaValidator-0.3.0.dist-info/METADATA
Flask_JsonSchemaValidator-0.3.0.dist-info/WHEEL
Flask_JsonSchemaValidator-0.3.0.dist-info/top_level.txt
Flask_JsonSchemaValidator-0.3.0.dist-info/RECORD
