Metadata-Version: 2.1
Name: Flask-JsonSchemaValidator
Version: 0.3.0
Summary: Basic JSON Schema Validator for the Flask web framework.
Home-page: https://github.com/wesclemens/Flask-JsonSchemaValidator
Author: William Clemens
Author-email: wesclemens@gmail.com
License: MIT
Keywords: Flask jsonschema validation json
Platform: UNKNOWN
Classifier: Development Status :: 4 - Beta
Classifier: Environment :: Web Environment
Classifier: Intended Audience :: Developers
Classifier: License :: OSI Approved :: MIT License
Classifier: Operating System :: OS Independent
Classifier: Programming Language :: Python
Classifier: Programming Language :: Python :: 3
Classifier: Topic :: Internet :: WWW/HTTP :: Dynamic Content
Classifier: Topic :: Software Development :: Libraries :: Python Modules
Requires-Dist: Flask (>=0.10.1)
Requires-Dist: jsonschema (>=2.4.0)
